numqy/__init__.py
numqy/classAll.py
numqy/printl.py
numqy-1.0.4.dist-info/METADATA
numqy-1.0.4.dist-info/WHEEL
numqy-1.0.4.dist-info/top_level.txt
numqy-1.0.4.dist-info/RECORD
