Metadata-Version: 2.1
Name: numqy
Version: 1.0.4
Summary: numqy is numpy's cousin
Home-page: https://www.python.org
Author: gting
Author-email: 1770919065@qq.com
License: MIT
Platform: UNKNOWN
